{
  "id": "golem-enc-04",
  "mode": "expanded",
  "title": "The Concordance Class",
  "description": "The golem has been tested with 1 ingredient. Deduce the reaction pattern and identify the target group.",
  "difficulty": "easy",
  "golem": {
    "chest": {
      "color": "G",
      "size": "L"
    },
    "ears": {
      "color": "B",
      "size": "L"
    }
  },
  "clues": [
    {
      "kind": "golem_test",
      "ingredient": 7,
      "chest_reacted": false,
      "ears_reacted": true
    },
    {
      "kind": "encyclopedia",
      "aspect": "G",
      "entries": [
        {
          "ingredient": 1,
          "sign": "-"
        },
        {
          "ingredient": 3,
          "sign": "-"
        },
        {
          "ingredient": 5,
          "sign": "-"
        }
      ]
    },
    {
      "kind": "encyclopedia",
      "aspect": "B",
      "entries": [
        {
          "ingredient": 5,
          "sign": "-"
        },
        {
          "ingredient": 6,
          "sign": "-"
        },
        {
          "ingredient": 8,
          "sign": "-"
        }
      ]
    }
  ],
  "questions": [
    {
      "kind": "golem_group",
      "group": "animators"
    }
  ],
  "solution": {
    "1": 5,
    "2": 8,
    "3": 2,
    "4": 4,
    "5": 7,
    "6": 6,
    "7": 1,
    "8": 3
  },
  "hints": [
    {
      "level": 1,
      "text": "The golem reacts to SIZE on a specific color channel.\nKnown tests:\n  ing7: chest=\u2717 ears=\u2713  \u2192  ears_only"
    },
    {
      "level": 2,
      "text": "Chest reacts to G+L. Ears react to B+L. Animation rule: Large reaction \u2192 '+', Small reaction \u2192 '\u2212'. So animation ingredients must have G+ AND B+. Cross-reference with the mixing clues to identify those ingredients."
    },
    {
      "level": 3,
      "text": "The animators are: ingredients [2, 4]. Alch: ing2\u2192PPP, ing4\u2192nPp."
    }
  ],
  "complexity": {
    "score": 10,
    "raw_score": 10,
    "clue_score": 0,
    "question_score": 0,
    "world_score": 0,
    "residual_worlds": 32
  }
}